hadoop_fs_wrapper/__init__.py
hadoop_fs_wrapper/_version.py
hadoop_fs_wrapper/models/__init__.py
hadoop_fs_wrapper/models/buffered_input_stream.py
hadoop_fs_wrapper/models/buffered_output_stream.py
hadoop_fs_wrapper/models/buffered_reader.py
hadoop_fs_wrapper/models/file_status.py
hadoop_fs_wrapper/models/fs_data_input_stream.py
hadoop_fs_wrapper/models/fs_data_output_stream.py
hadoop_fs_wrapper/models/glob_filter.py
hadoop_fs_wrapper/models/hadoop_file_status.py
hadoop_fs_wrapper/models/hadoop_fs_path.py
hadoop_fs_wrapper/models/input_stream_reader.py
hadoop_fs_wrapper/models/remote_iterator.py
hadoop_fs_wrapper/models/uri.py
hadoop_fs_wrapper/wrappers/__init__.py
hadoop_fs_wrapper/wrappers/file_system.py
hadoop_fs_wrapper/wrappers/hadoop_fs_wrapper.py
hadoop_fs_wrapper-0.7.1.dist-info/LICENSE
hadoop_fs_wrapper-0.7.1.dist-info/METADATA
hadoop_fs_wrapper-0.7.1.dist-info/WHEEL
hadoop_fs_wrapper-0.7.1.dist-info/RECORD
