Metadata-Version: 2.1
Name: hadoop-fs-wrapper
Version: 0.7.1
Summary: Python Wrapper for Hadoop Java API
Home-page: https://github.com/SneaksAndData/hadoop-fs-wrapper
License: MIT
Author: ECCO Sneaks & Data
Author-email: esdsupport@ecco.com
Maintainer: GZU
Maintainer-email: gzu@ecco.com
Requires-Python: >=3.11,<3.13
Classifier: License :: OSI Approved :: MIT License
Classifier: Programming Language :: Python :: 3
Classifier: Programming Language :: Python :: 3.11
Classifier: Programming Language :: Python :: 3.12
Requires-Dist: pyspark (>=3.5,<3.6)
Project-URL: Repository, https://github.com/SneaksAndData/hadoop-fs-wrapper
